analysis/__init__.py
analysis/beaten_distances.py
analysis/flat_race_level_par_rating.py
analysis/forecasting/__init__.py
analysis/forecasting/form_forecast.py
analysis/forecasting/form_forecaster.py
analysis/forecasting/form_predictor.py
analysis/forecasting/future_form_factors/__init__.py
analysis/forecasting/future_form_factors/experience_improvement_bonus.py
analysis/forecasting/future_form_factors/future_form_factor.py
analysis/forecasting/future_form_factors/handicap_debut_bonus.py
analysis/forecasting/future_form_factors/three_year_old_vs_older_bonus.py
analysis/forecasting/strategies/__init__.py
analysis/forecasting/strategies/form_forecast_strategy.py
analysis/forecasting/strategies/min_mode_max_triangular.py
analysis/forecasting/strategies/norm_around_weighted_mean.py
analysis/forecasting/strategies/repeat_lto.py
analysis/forecasting/strategies/run_to_race_level.py
analysis/forecasting/weighting_factors/__init__.py
analysis/forecasting/weighting_factors/conditions_likeness.py
analysis/forecasting/weighting_factors/rating_solidity.py
analysis/forecasting/weighting_factors/weighting_factor.py
analysis/going.py
analysis/likeness.py
analysis/pricing/__init__.py
analysis/pricing/monte_carlo_simulator.py
analysis/pricing/pricer.py
analysis/pricing/ratings_to_odds_converter.py
analysis/pricing/strategies/__init__.py
analysis/pricing/strategies/alpha.py
analysis/pricing/strategies/monte_carlo.py
analysis/pricing/strategies/pricing_strategy.py
analysis/race_career.py
analysis/race_conditions.py
analysis/race_datetime.py
analysis/race_distance.py
analysis/racecourse.py
analysis/rating/__init__.py
analysis/rating/adjustments/__init__.py
analysis/rating/adjustments/ease_of_win_adjustment.py
analysis/rating/adjustments/rating_adjustment.py
analysis/rating/form_rater.py
analysis/rating/form_rating.py
analysis/rating/jockey_rating.py
analysis/rating/performance_context.py
analysis/rating/race_performance.py
analysis/rating/race_result.py
handykapp_analysis-0.20.1.dist-info/METADATA
handykapp_analysis-0.20.1.dist-info/WHEEL
handykapp_analysis-0.20.1.dist-info/RECORD
