Metadata-Version: 2.1
Name: handykapp-analysis
Version: 0.20.1
Summary: Analysis tools for horseracing data
Author: peaky76
Author-email: robertjamespeacock@gmail.com
Requires-Python: >=3.11,<3.12
Classifier: Programming Language :: Python :: 3
Classifier: Programming Language :: Python :: 3.11
Requires-Dist: horsetalk (>=0.22.3,<0.23.0)
Requires-Dist: peak-utility (>=0.6.0,<0.7.0)
Requires-Dist: pendulum (>=3.0.0,<4.0.0)
Requires-Dist: pybet (>=0.6.2,<0.9.0)
Requires-Dist: scipy (>=1.12.0,<2.0.0)
